<annotation>
	<folder>traffic-sign</folder>
	<filename>IMG_2243.JPG</filename>
	<path>D:\d\traffic-sign\IMG_2243.JPG</path>
	<source>
		<database>Unknown</database>
	</source>
	<size>
		<width>1024</width>
		<height>1024</height>
		<depth>3</depth>
	</size>
	<segmented>0</segmented>
	<object>
		<name>trafikisiklari</name>
		<pose>Unspecified</pose>
		<truncated>0</truncated>
		<difficult>0</difficult>
		<bndbox>
			<xmin>453</xmin>
			<ymin>359</ymin>
			<xmax>631</xmax>
			<ymax>478</ymax>
		</bndbox>
	</object>
</annotation>
