<annotation>
	<folder>Part7_Alperen</folder>
	<filename>15622.png</filename>
	<path>C:\Users\ahmet.alperen.bulut\Desktop\Part7_Alperen\15622.png</path>
	<source>
		<database>Unknown</database>
	</source>
	<size>
		<width>1280</width>
		<height>720</height>
		<depth>3</depth>
	</size>
	<segmented>0</segmented>
	<object>
		<name>Park yeri</name>
		<pose>Unspecified</pose>
		<truncated>0</truncated>
		<difficult>0</difficult>
		<bndbox>
			<xmin>735</xmin>
			<ymin>187</ymin>
			<xmax>756</xmax>
			<ymax>215</ymax>
		</bndbox>
	</object>
	<object>
		<name>Park yeri</name>
		<pose>Unspecified</pose>
		<truncated>0</truncated>
		<difficult>0</difficult>
		<bndbox>
			<xmin>587</xmin>
			<ymin>199</ymin>
			<xmax>603</xmax>
			<ymax>221</ymax>
		</bndbox>
	</object>
	<object>
		<name>Park yeri</name>
		<pose>Unspecified</pose>
		<truncated>0</truncated>
		<difficult>0</difficult>
		<bndbox>
			<xmin>529</xmin>
			<ymin>204</ymin>
			<xmax>546</xmax>
			<ymax>226</ymax>
		</bndbox>
	</object>
</annotation>
