<annotation>
	<folder>traffic-sign-data</folder>
	<filename>duraklamakveparkyasaktir_215.jpg</filename>
	<path>/traffic-sign-data/duraklamakveparkyasaktir_215.jpg</path>
	<source>
		<database>Unspecified</database>
	</source>
	<size>
		<width>1920</width>
		<height>1080</height>
		<depth>3</depth>
	</size>
	<object>
		<name>duraklamakveparkyasaktir</name>
		<pose>Unspecified</pose>
		<truncated>Unspecified</truncated>
		<difficult>Unspecified</difficult>
		<bndbox>
			<xmin>88</xmin>
			<ymin>509</ymin>
			<xmax>173</xmax>
			<ymax>583</ymax>
		</bndbox>
	</object>
</annotation>