<annotation>
	<folder>traffic-sign-data</folder>
	<filename>girisiolmayanyol_151.jpg</filename>
	<path>/traffic-sign-data/girisiolmayanyol_151.jpg</path>
	<source>
		<database>Unspecified</database>
	</source>
	<size>
		<width>1920</width>
		<height>1080</height>
		<depth>3</depth>
	</size>
	<object>
		<name>girisiolmayanyol</name>
		<pose>Unspecified</pose>
		<truncated>Unspecified</truncated>
		<difficult>Unspecified</difficult>
		<bndbox>
			<xmin>1732</xmin>
			<ymin>397</ymin>
			<xmax>1796</xmax>
			<ymax>473</ymax>
		</bndbox>
	</object>
</annotation>