<annotation>
	<folder>Part7_Alperen</folder>
	<filename>15727.png</filename>
	<path>C:\Users\ahmet.alperen.bulut\Desktop\Part7_Alperen\15727.png</path>
	<source>
		<database>Unknown</database>
	</source>
	<size>
		<width>1280</width>
		<height>720</height>
		<depth>3</depth>
	</size>
	<segmented>0</segmented>
	<object>
		<name>Park yeri</name>
		<pose>Unspecified</pose>
		<truncated>0</truncated>
		<difficult>0</difficult>
		<bndbox>
			<xmin>1199</xmin>
			<ymin>129</ymin>
			<xmax>1249</xmax>
			<ymax>196</ymax>
		</bndbox>
	</object>
	<object>
		<name>Park yeri</name>
		<pose>Unspecified</pose>
		<truncated>0</truncated>
		<difficult>0</difficult>
		<bndbox>
			<xmin>792</xmin>
			<ymin>131</ymin>
			<xmax>835</xmax>
			<ymax>181</ymax>
		</bndbox>
	</object>
	<object>
		<name>Park yeri</name>
		<pose>Unspecified</pose>
		<truncated>0</truncated>
		<difficult>0</difficult>
		<bndbox>
			<xmin>655</xmin>
			<ymin>145</ymin>
			<xmax>685</xmax>
			<ymax>186</ymax>
		</bndbox>
	</object>
	<object>
		<name>Park etmek yasaktir</name>
		<pose>Unspecified</pose>
		<truncated>0</truncated>
		<difficult>0</difficult>
		<bndbox>
			<xmin>981</xmin>
			<ymin>123</ymin>
			<xmax>1029</xmax>
			<ymax>172</ymax>
		</bndbox>
	</object>
</annotation>
