<?xml version='1.0' encoding='UTF-8'?>
<annotation>
	<folder>bluetooth</folder>
	<filename>savhascelik_360.xml</filename>
	<path>D:\yuksek_lisans\tez\kod\resimler\bluetooth\savhascelik_360.xml</path>
	<source>
		<database>Unknown</database>
	</source>
	<size>
		<width>2160</width>
		<height>1080</height>
		<depth>3</depth>
	</size>
	<segmented>0</segmented>
	<object>
		<name>Sola Dönüş Yasak Tabelası</name>
		<pose>Unspecified</pose>
		<truncated>0</truncated>
		<difficult>0</difficult>
		<bndbox>
			<xmin>667</xmin>
			<ymin>635</ymin>
			<xmax>733</xmax>
			<ymax>698</ymax>
		</bndbox>
	</object>
	<object>
		<name>Yeşil Işık Tabelası</name>
		<pose>Unspecified</pose>
		<truncated>0</truncated>
		<difficult>0</difficult>
		<bndbox>
			<xmin>535</xmin>
			<ymin>529</ymin>
			<xmax>616</xmax>
			<ymax>678</ymax>
		</bndbox>
	</object>
	<object>
		<name>Yeşil Işık Tabelası</name>
		<pose>Unspecified</pose>
		<truncated>0</truncated>
		<difficult>0</difficult>
		<bndbox>
			<xmin>1158</xmin>
			<ymin>190</ymin>
			<xmax>1214</xmax>
			<ymax>326</ymax>
		</bndbox>
	</object>
	<object>
		<name>Yeşil Işık Tabelası</name>
		<pose>Unspecified</pose>
		<truncated>0</truncated>
		<difficult>0</difficult>
		<bndbox>
			<xmin>1944</xmin>
			<ymin>624</ymin>
			<xmax>2034</xmax>
			<ymax>753</ymax>
		</bndbox>
	</object>
	<object>
		<name>Kırmızı Işık Tabelası</name>
		<pose>Unspecified</pose>
		<truncated>0</truncated>
		<difficult>0</difficult>
		<bndbox>
			<xmin>633</xmin>
			<ymin>547</ymin>
			<xmax>679</xmax>
			<ymax>628</ymax>
		</bndbox>
	</object>
</annotation>