<?xml version='1.0' encoding='UTF-8'?>
<annotation>
	<folder>bluetooth</folder>
	<filename>savhascelik_433.xml</filename>
	<path>D:\yuksek_lisans\tez\kod\resimler\bluetooth\savhascelik_433.xml</path>
	<source>
		<database>Unknown</database>
	</source>
	<size>
		<width>2160</width>
		<height>1080</height>
		<depth>3</depth>
	</size>
	<segmented>0</segmented>
	<object>
		<name>Kırmızı Işık Tabelası</name>
		<pose>Unspecified</pose>
		<truncated>0</truncated>
		<difficult>0</difficult>
		<bndbox>
			<xmin>1430</xmin>
			<ymin>401</ymin>
			<xmax>1454</xmax>
			<ymax>455</ymax>
		</bndbox>
	</object>
	<object>
		<name>Kırmızı Işık Tabelası</name>
		<pose>Unspecified</pose>
		<truncated>0</truncated>
		<difficult>0</difficult>
		<bndbox>
			<xmin>1182</xmin>
			<ymin>248</ymin>
			<xmax>1204</xmax>
			<ymax>313</ymax>
		</bndbox>
	</object>
	<object>
		<name>Kırmızı Işık Tabelası</name>
		<pose>Unspecified</pose>
		<truncated>0</truncated>
		<difficult>0</difficult>
		<bndbox>
			<xmin>851</xmin>
			<ymin>386</ymin>
			<xmax>877</xmax>
			<ymax>441</ymax>
		</bndbox>
	</object>
	<object>
		<name>U Dönüşü Yasak Tabelası</name>
		<pose>Unspecified</pose>
		<truncated>0</truncated>
		<difficult>0</difficult>
		<bndbox>
			<xmin>854</xmin>
			<ymin>445</ymin>
			<xmax>890</xmax>
			<ymax>485</ymax>
		</bndbox>
	</object>
</annotation>