<?xml version='1.0' encoding='UTF-8'?>
<annotation>
	<folder>bluetooth</folder>
	<filename>savhascelik_234.xml</filename>
	<path>D:\yuksek_lisans\tez\kod\resimler\bluetooth\savhascelik_234.xml</path>
	<source>
		<database>Unknown</database>
	</source>
	<size>
		<width>2160</width>
		<height>1080</height>
		<depth>3</depth>
	</size>
	<segmented>0</segmented>
	<object>
		<name>Işıklı İşaret Cihazı</name>
		<pose>Unspecified</pose>
		<truncated>0</truncated>
		<difficult>0</difficult>
		<bndbox>
			<xmin>604</xmin>
			<ymin>201</ymin>
			<xmax>693</xmax>
			<ymax>322</ymax>
		</bndbox>
	</object>
	<object>
		<name>Hız Limiti 30 Tabelası</name>
		<pose>Unspecified</pose>
		<truncated>0</truncated>
		<difficult>0</difficult>
		<bndbox>
			<xmin>613</xmin>
			<ymin>330</ymin>
			<xmax>683</xmax>
			<ymax>437</ymax>
		</bndbox>
	</object>
	<object>
		<name>Dönüş Adası Tabelası</name>
		<pose>Unspecified</pose>
		<truncated>0</truncated>
		<difficult>0</difficult>
		<bndbox>
			<xmin>1190</xmin>
			<ymin>465</ymin>
			<xmax>1212</xmax>
			<ymax>496</ymax>
		</bndbox>
	</object>
	<object>
		<name>Sola Dönülebilir Veya İleri Gidilebilir Tabelası</name>
		<pose>Unspecified</pose>
		<truncated>0</truncated>
		<difficult>0</difficult>
		<bndbox>
			<xmin>1187</xmin>
			<ymin>437</ymin>
			<xmax>1209</xmax>
			<ymax>461</ymax>
		</bndbox>
	</object>
</annotation>