<annotation>
	<folder>sola_donulmez</folder>
	<filename>372.png</filename>
	<path>/home/furkan/Desktop/Hazine/frames/klasor2/sola_donulmez/372.png</path>
	<source>
		<database>Unknown</database>
	</source>
	<size>
		<width>1280</width>
		<height>720</height>
		<depth>3</depth>
	</size>
	<segmented>0</segmented>
	<object>
		<name>Sola donulmez</name>
		<pose>Unspecified</pose>
		<truncated>0</truncated>
		<difficult>0</difficult>
		<bndbox>
			<xmin>730</xmin>
			<ymin>92</ymin>
			<xmax>761</xmax>
			<ymax>124</ymax>
		</bndbox>
	</object>
</annotation>
